Metadata-Version: 2.1
Name: odoo12-addon-account-due-list-payment-mode
Version: 12.0.1.0.0.99.dev14
Summary: Payment Due List Payment Mode
Home-page: https://github.com/OCA/account-payment
Author: Obertix Free Solutions, Tecnativa, Odoo Community Association (OCA),
Author-email: support@odoo-community.org
License: AGPL-3
Platform: UNKNOWN
Classifier: Programming Language :: Python
Classifier: Framework :: Odoo
Classifier: Framework :: Odoo :: 12.0
Classifier: License :: OSI Approved :: GNU Affero General Public License v3
Requires-Python: >=3.5
Requires-Dist: odoo12-addon-account-due-list
Requires-Dist: odoo12-addon-account-payment-partner
Requires-Dist: odoo <12.1dev,>=12.0a
